telerdac/__init__.py
telerdac/telerdac.py
telerdac/cmd/__init__.py
telerdac/cmd/cmd.cpython-36m-aarch64-linux-gnu.so
telerdac/const/__init__.py
telerdac/const/click_setting.cpython-36m-aarch64-linux-gnu.so
telerdac/utils/__init__.py
telerdac/utils/device_utils.cpython-36m-aarch64-linux-gnu.so
telerdac/utils/file_utils.cpython-36m-aarch64-linux-gnu.so
telerdac/utils/license_utils.cpython-36m-aarch64-linux-gnu.so
telerdac-0.1.0.dist-info/METADATA
telerdac-0.1.0.dist-info/WHEEL
telerdac-0.1.0.dist-info/entry_points.txt
telerdac-0.1.0.dist-info/top_level.txt
telerdac-0.1.0.dist-info/RECORD
