Metadata-Version: 2.1
Name: telerdac
Version: 0.1.0
Summary: Command line toolkit for tele rdac
Home-page: UNKNOWN
Author: imason
Author-email: moy7@chinatelecom.cn
License: UNKNOWN
Keywords: telerdac
Platform: UNKNOWN
Classifier: Programming Language :: Python :: 3
Classifier: License :: OSI Approved :: MIT License
Classifier: Operating System :: OS Independent
Requires-Python: >=3.6,
Requires-Dist: Click (>=8.0.4)
Requires-Dist: rsa (==4.9)
